aa2unicode/__init__.py
aa2unicode/main.py
aa2unicode-0.2.2.dist-info/LICENSE
aa2unicode-0.2.2.dist-info/METADATA
aa2unicode-0.2.2.dist-info/WHEEL
aa2unicode-0.2.2.dist-info/entry_points.txt
aa2unicode-0.2.2.dist-info/top_level.txt
aa2unicode-0.2.2.dist-info/RECORD
