Metadata-Version: 2.1
Name: aa2unicode
Version: 0.2.2
Summary: ASCII Artwork to Unicode box characters
Author-email: Tom Pusateri <pusateri@bangj.com>
Project-URL: Homepage, https://github.com/pusateri/aa2unicode
Project-URL: Bug Tracker, https://github.com/pusateri/aa2unicode/issues
Classifier: Programming Language :: Python :: 3
Classifier: License :: OSI Approved :: MIT License
Classifier: Operating System :: OS Independent
Requires-Python: >=3.7
License-File: LICENSE
